model/__init__.py
model/application/__init__.py
model/application/woe_modules/__init__.py
model/application/woe_modules/application_main_settings.py
model/application/woe_modules/application_modules.py
model/balance_sheet_module/__init__.py
model/balance_sheet_module/section_01_compute_indicator/__init__.py
model/balance_sheet_module/section_01_compute_indicator/main.py
model/balance_sheet_module/section_02_u_shape_treatment/__init__.py
model/balance_sheet_module/section_02_u_shape_treatment/main.py
model/balance_sheet_module/section_03_88_treatment/__init__.py
model/balance_sheet_module/section_03_88_treatment/main.py
model/balance_sheet_module/section_04_univariate_analysis/__init__.py
model/balance_sheet_module/section_04_univariate_analysis/main.py
model/balance_sheet_module/section_05_correlation/__init__.py
model/balance_sheet_module/section_05_correlation/main.py
model/balance_sheet_module/section_06_logistic_transformation/__init__.py
model/balance_sheet_module/section_06_logistic_transformation/main.py
model/balance_sheet_module/section_07_combinatorial/__init__.py
model/balance_sheet_module/section_07_combinatorial/main.py
model/balance_sheet_module/section_08_bootstrapping/__init__.py
model/balance_sheet_module/section_08_bootstrapping/main.py
model/balance_sheet_module/utils/__init__.py
model/balance_sheet_module/utils/indeterminate_forms.py
model/balance_sheet_module/utils/indicator.py
model/balance_sheet_module/utils/main_general_setting.py
model/balance_sheet_module/utils/u_shape.py
model/balance_sheet_module/utils/univariate_analysis.py
model/dtd_module/__init__.py
model/dtd_module/section_01_computation/__init__.py
model/dtd_module/section_01_computation/dtd.py
model/integration/__init__.py
model/integration/main_application.py
model/qualitative_questionnaire/__init__.py
model/qualitative_questionnaire/section_01_process_qq/__init__.py
model/qualitative_questionnaire/section_01_process_qq/main.py
cracfunctions-1.2.0.dist-info/METADATA
cracfunctions-1.2.0.dist-info/WHEEL
cracfunctions-1.2.0.dist-info/top_level.txt
cracfunctions-1.2.0.dist-info/RECORD
